LICENSE.rst
MANIFEST.in
README.md
README.rst
setup.cfg
setup.py
src/wiggles/__init__.py
src/wiggles/functions.py
src/wiggles/signals.py
src/wiggles/symbols.py
src/wiggles.egg-info/PKG-INFO
src/wiggles.egg-info/SOURCES.txt
src/wiggles.egg-info/dependency_links.txt
src/wiggles.egg-info/requires.txt
src/wiggles.egg-info/top_level.txt