Metadata-Version: 2.1
Name: wiggles
Version: 2.5.8
Summary: This library makes signal processing easy! A great tool for students to easily visualise and test their sigals virtually. Whether you're working with continuous or discrete signals, Wiggles provides a wide range of functionalities to make signal processing straightforward and intuitive. It supports operations in both the time domain and frequency domain, including Fast Fourier Transform (FFT) and inverse FFT, and allows for easy conversion between different representations.
Home-page: https://github.com/Kawai-Senpai/Wiggles
Download-URL: https://github.com/Kawai-Senpai/Wiggles
Author: Ranit Bhowmick
Author-email: bhowmickranitking@duck.com
License: MIT License with attribution requirement
Keywords: Signal Processing,Education,Discrete signal,Continuous signal,Basic signal operations
License-File: LICENSE.rst
